pylinkedlist.py
pylinkedlist-0.1.0.dist-info/LICENSE
pylinkedlist-0.1.0.dist-info/METADATA
pylinkedlist-0.1.0.dist-info/WHEEL
pylinkedlist-0.1.0.dist-info/top_level.txt
pylinkedlist-0.1.0.dist-info/RECORD
