Metadata-Version: 2.1
Name: pylinkedlist
Version: 0.1.0
Summary: A Python package to work with LinkedList.
Home-page: https://github.com/HiteshAgarwal1/Python-LinkedList
Author: Hitesh Agarwal
Author-email: contact@hiteshagarwal.com
License: MIT
Download-URL: https://github.com/HiteshAgarwal1/Python-LinkedList/archive/0.0.1.tar.gz
Keywords: linked list,list,python linked list
Platform: UNKNOWN
Classifier: License :: OSI Approved :: MIT License
Classifier: Programming Language :: Python :: 3
Classifier: Programming Language :: Python :: 3.7
Classifier: Operating System :: OS Independent
Classifier: Intended Audience :: Developers
Classifier: Intended Audience :: Education
Classifier: Intended Audience :: End Users/Desktop
Classifier: Intended Audience :: Science/Research
